LICENSE
MANIFEST.in
README.rst
setup.py
django_atlassian/__init__.py
django_atlassian/addon.py
django_atlassian/admin.py
django_atlassian/apps.py
django_atlassian/decorators.py
django_atlassian/middleware.py
django_atlassian/router.py
django_atlassian/urls.py
django_atlassian/views.py
django_atlassian.egg-info/PKG-INFO
django_atlassian.egg-info/SOURCES.txt
django_atlassian.egg-info/dependency_links.txt
django_atlassian.egg-info/requires.txt
django_atlassian.egg-info/top_level.txt
django_atlassian/backends/__init__.py
django_atlassian/backends/common/__init__.py
django_atlassian/backends/common/base.py
django_atlassian/backends/common/compiler.py
django_atlassian/backends/confluence/__init__.py
django_atlassian/backends/confluence/base.py
django_atlassian/backends/confluence/compiler.py
django_atlassian/backends/jira/__init__.py
django_atlassian/backends/jira/base.py
django_atlassian/backends/jira/compiler.py
django_atlassian/migrations/0001_initial.py
django_atlassian/migrations/__init__.py
django_atlassian/models/__init__.py
django_atlassian/models/confluence.py
django_atlassian/models/connect.py
django_atlassian/models/fields.py
django_atlassian/models/jira.py