Metadata-Version: 1.1
Name: django-atlassian
Version: 0.1.2
Summary: Django app for interact with atlassian libraries such as JIRA and Confluence.
Home-page: https://www.fluendo.com/
Author: Fluendo
Author-email: web-dev@fluendo.com
License: MIT License
Platform: UNKNOWN
Classifier: Environment :: Web Environment
Classifier: Framework :: Django
Classifier: Intended Audience :: Developers
Classifier: License :: OSI Approved :: MIT License
Classifier: Operating System :: OS Independent
Classifier: Programming Language :: Python
Classifier: Programming Language :: Python :: 3.5
Classifier: Programming Language :: Python :: 3.6
Classifier: Topic :: Internet :: WWW/HTTP
Classifier: Topic :: Internet :: WWW/HTTP :: Dynamic Content
